{
  "font_family": "Roboto",
  "height": 400,
  "legend_align": "right",
  "series_list": [
    {
      "name": "Female",
      "data": [
        161.2,
        51.6,
        167.5,
        59,
        159.5,
        49.2,
        157,
        63,
        155.8,
        53.6,
        170,
        59,
        159.1,
        47.6,
        166,
        69.8,
        176.2,
        66.8,
        160.2,
        75.2,
        172.5,
        55.2,
        170.9,
        54.2,
        172.9,
        62.5,
        153.4,
        42,
        160,
        50,
        147.2,
        49.8,
        168.2,
        49.2,
        175,
        73.2,
        157,
        47.8,
        167.6,
        68.8,
        159.5,
        50.6,
        175,
        82.5,
        166.8,
        57.2,
        176.5,
        87.8,
        170.2,
        72.8
      ]
    },
    {
      "name": "Male",
      "data": [
        174,
        65.6,
        175.3,
        71.8,
        193.5,
        80.7,
        186.5,
        72.6,
        187.2,
        78.8,
        181.5,
        74.8,
        184,
        86.4,
        184.5,
        78.4,
        175,
        62,
        184,
        81.6,
        180,
        76.6,
        177.8,
        83.6,
        192,
        90,
        176,
        74.6,
        174,
        71,
        184,
        79.6,
        192.7,
        93.8,
        171.5,
        70,
        173,
        72.4,
        176,
        85.9,
        176,
        78.8,
        180.5,
        77.8,
        172.7,
        66.2,
        176,
        86.4,
        173.5,
        81.8
      ]
    }
  ],
  "series_symbol_sizes": [
    6,
    6
  ],
  "sub_title_align": "left",
  "sub_title_text": "Data from: Heinz 2003",
  "theme": "grafana",
  "title_align": "left",
  "title_text": "Male and female height and weight distribution",
  "type": "scatter",
  "width": 600,
  "x_axis_config": {
    "axis_min": 140,
    "axis_max": 200,
    "axis_formatter": "{c} cm"
  },
  "y_axis_configs": [
    {
      "axis_min": 40,
      "axis_max": 100,
      "axis_formatter": "{c} kg"
    }
  ]
}